pysui_sdk/__init__.py
pysui_sdk/models.py
pysui_sdk/provider.py
pysui_sdk/rpc_tx_data_serializer.py
pysui_sdk/signer.py
pysui_sdk/signer_with_provider.py
pysui_sdk/wallet.py
pysui_sdk-1.0.7.dist-info/METADATA
pysui_sdk-1.0.7.dist-info/WHEEL
pysui_sdk-1.0.7.dist-info/top_level.txt
pysui_sdk-1.0.7.dist-info/RECORD
