Metadata-Version: 2.1
Name: pysui-sdk
Version: 1.0.7
Summary: UNKNOWN
Home-page: https://github.com/satisfywithmylife/sui_python_sdk
Author: shawngmy
Author-email: shawngmy@gmail.com
License: UNKNOWN
Platform: UNKNOWN
Classifier: Programming Language :: Python :: 3
Requires-Python: >=3.7
Requires-Dist: httpx
Requires-Dist: pynacl
